auth_playground/__init__.py
auth_playground/cli.py
auth_playground/decorators.py
auth_playground/endpoints.py
auth_playground/forms.py
auth_playground/i18n.py
auth_playground/oauth.py
auth_playground/session.py
auth_playground/specs.py
auth_playground/static/css/custom.css
auth_playground/static/css/pico.colors.min.css
auth_playground/static/css/pico.min.css
auth_playground/static/js/copy-token.js
auth_playground/templates/configure_client.html
auth_playground/templates/configure_server.html
auth_playground/templates/layout.html
auth_playground/templates/playground.html
auth_playground/templates/policy.html
auth_playground/templates/server_specs.html
auth_playground/templates/specs.html
auth_playground/templates/static-configuration.html
auth_playground/templates/tokens.html
auth_playground/templates/tos.html
auth_playground/translations/README.md
auth_playground/translations/messages.pot
auth_playground/translations/fr/LC_MESSAGES/messages.mo
auth_playground/translations/fr/LC_MESSAGES/messages.po
auth_playground-0.1.7.dist-info/METADATA
auth_playground-0.1.7.dist-info/WHEEL
auth_playground-0.1.7.dist-info/entry_points.txt
auth_playground-0.1.7.dist-info/licenses/LICENSE.md
auth_playground-0.1.7.dist-info/RECORD
