Metadata-Version: 2.4
Name: auth-playground
Version: 0.1.7
Summary: Demonstration OpenID Connect Client
Project-URL: repository, https://github.com/yaal-coop/auth-playground
Author-email: Yaal Coop <contact@yaal.coop>
Maintainer-email: Éloi Rivard <eloi@yaal.coop>
License: MIT
License-File: LICENSE.md
Keywords: authentication,identity,oauth,oauth2,oidc,openid
Requires-Python: >=3.10
Requires-Dist: authlib>=1.6.5
Requires-Dist: cachelib>=0.10.0
Requires-Dist: flask-babel>=4.0.0
Requires-Dist: flask-session>=0.8.0
Requires-Dist: flask-wtf>=1.2.0
Requires-Dist: flask>=3.1.2
Requires-Dist: python-dotenv>=1.0.0
Requires-Dist: requests>=2.32.5
